{
    "title": "Tündér Kaland",
    "max-trial-retries": 3,

    "scenes": [
        {
            "type": "trial-camera",
            "content-html": "hghghgh"
        },
        {
            "type": "trial-location",
            "sytle": "kids-game.css",
            "content-html": "Ez a játék a Soproni Erzsébet Kertben játszható. Ha odaértetek, automatikusan indul az első feladat."
        },
        {
            "type": "story",
            "sytle": "kids-game.css",
            "content-html": "Kedves Tündér-kalandozó! Az applikáció segítségével játékosan tanulhatsz a természetről. Az lesz a feladatod, hogy fákat, virágokat és más növényeket fotózz le a kezedben tartott mobil eszköz segítségével. A fotókat pedig együtt kielemezzük, összehasonlítjuk. Kezdjük is el!",
            "next-button-text": "Rajta"
        },
        {
            "type": "trial-camera",
            "sytle": "kids-game.css",
            "content-html": "Először is készíts egy fényképet egy szép nagy fáról!",
            "success-animation": "thumbs-up.gif" 
        },
        {
            "type": "trial-camera",
            "sytle": "kids-game.css",
            "content-html": "Nagyon jó kép lett! Most pedig fotózz le egy bokrot!",
            "success-animation": "thumbs-up.gif" 
        },
        {
            "type": "trial-camera-ar",
            "sytle": "kids-game.css",
            "content-html": "Ügyes vagy! A harmadik kép egy fűszál vagy egy virág legyen!",
            "content-ar": "fairy.model",
            "success-animation": "style-change.gif" 
        },
        {
            "type": "story",
            "sytle": "fairy-game.css",
            "content-html": "Szia! Trilla vagyok. Az apukám, a Tündér Király, nagy bajban van! Csak az ember-gyerekek tudnak nekünk segíteni. Rájöttem, hogy egy varázslattal tudok nektek üzenni ezeken a mobil-izéken, ami mindig a kezetekben van. Így együtt talán meg tudjuk oldani a rejtélyt és megmenthetjük apukámat a Tündér Királyt, meg az egész Tündér Királyságot. De sietnünk kell, a varázslatom egy idő múlva erejét veszti! Segítesz? Ugye segítesz?",
            "next-button-text": "Igen",
            "exit-button-hide": false, 
            "exit-button-text": "Nem"
        },
        {
            "content-html": "Lorem ipsum dolor sit amet, consectetur adipiscing elit."
        },
        {
            "content-html": "Lorem ipsum dolor sit amet, consectetur adipiscing elit. Nunc ullamcorper ipsum eu tincidunt imperdiet."
        },
        {
            "type": "trial-options",
            "options": ["13", "17", "21"],
            "solution": "21",
            "content-html": "Lorem ipsum dolor sit amet, consectetur adipiscing elit."
        },
        {
            "content-html": "Lorem ipsum."
        }
    ],

    "ending": {
        "success": {
            "content-html": "Lorem ipsum :)"
        },
        "failure": {
            "content-html": "Lorem ipsum :("
        }
    }
}